siweilib/__init__.py
siweilib/general.py
siweilib/filez/__init__.py
siweilib/filez/chash.py
siweilib/filez/lib.py
siweilib/filez/test.py
siweilib-0.0.2.11.dist-info/DESCRIPTION.rst
siweilib-0.0.2.11.dist-info/METADATA
siweilib-0.0.2.11.dist-info/RECORD
siweilib-0.0.2.11.dist-info/WHEEL
siweilib-0.0.2.11.dist-info/metadata.json
siweilib-0.0.2.11.dist-info/top_level.txt
